algofuzz/__init__.py
algofuzz/__main__.py
algofuzz/colors.py
algofuzz/enums.py
algofuzz/exceptions.py
algofuzz/param_tester.py
algofuzz/datasets/__init__.py
algofuzz/datasets/bubble_gen.py
algofuzz/datasets/glass.py
algofuzz/datasets/prev_bubble_gen.py
algofuzz/datasets/seeds.py
algofuzz/fcm/__init__.py
algofuzz/fcm/base_fcm.py
algofuzz/fcm/eta_fcm.py
algofuzz/fcm/fcm.py
algofuzz/fcm/fcplus1m.py
algofuzz/fcm/nonoptimized_fp3cm.py
algofuzz/fcm/nonoptimized_fpcm.py
algofuzz/fcm/possibilistic_fcm.py
algofuzz/fcm/stpfcm.py
algofuzz/validation/__init__.py
algofuzz/validation/confusion_matrix.py
algofuzz/validation/validity_index.py
algofuzz-0.1.1.dist-info/METADATA
algofuzz-0.1.1.dist-info/WHEEL
algofuzz-0.1.1.dist-info/top_level.txt
algofuzz-0.1.1.dist-info/RECORD
