Metadata-Version: 2.1
Name: algofuzz
Version: 0.1.1
Summary: Framework for popular fuzzy c-means clustering algorithms from literature
Home-page: https://github.com/naghim/algofuzz
Author: naghim
Author-email: naghi.mirtill@gmail.com
Classifier: Development Status :: 1 - Planning
Classifier: Programming Language :: Python :: 3
Classifier: Operating System :: OS Independent
Classifier: Topic :: System :: Clustering
Requires-Python: >=3.8
Requires-Dist: pydantic
Requires-Dist: scikit-learn
Requires-Dist: matplotlib
Requires-Dist: p-tqdm
